Metadata-Version: 2.1
Name: beepki
Version: 0.0.1
Summary: A simple module for making signal when exiting from a block
Home-page: https://github.com/zeionara/beep
Author: Zeio Nara
Author-email: zeionara@gmail.com
License: Apache 2.0
Project-URL: Documentation, https://github.com/zeionara/beep#readme
Project-URL: Bug Reports, https://github.com/zeionara/beep/issues
Project-URL: Source Code, https://github.com/zeionara/beep
Classifier: Intended Audience :: Developers
Classifier: License :: OSI Approved :: MIT License
Classifier: Programming Language :: Python :: 3.11
License-File: LICENSE
